puzh/__init__.py
puzh/puzh.py
puzh-1.1.2.dist-info/LICENSE
puzh-1.1.2.dist-info/METADATA
puzh-1.1.2.dist-info/WHEEL
puzh-1.1.2.dist-info/top_level.txt
puzh-1.1.2.dist-info/zip-safe
puzh-1.1.2.dist-info/RECORD
