Metadata-Version: 2.1
Name: puzh
Version: 1.1.2
Summary: Easily send messages to Telegram
Home-page: https://github.com/puzh/puzh.py
Author: puzh.it
License: MIT
Keywords: puzh,push,telegram,bot,notification
Platform: UNKNOWN
Classifier: Development Status :: 5 - Production/Stable
Classifier: Intended Audience :: Developers
Classifier: License :: OSI Approved :: MIT License
Classifier: Natural Language :: English
Classifier: Programming Language :: Python :: 3
Classifier: Programming Language :: Python :: 3.5
Classifier: Programming Language :: Python :: 3.6
Requires-Python: >=3
Requires-Dist: requests (>=2.19.1)
